{"definitions":[{"category":"computationalOperation","hasSorry":false,"instanceArgTypes":[],"instanceDisposition":null,"instanceLawfulClass":null,"instanceOf":null,"isPrivate":false,"name":"ProbabilityTheory.«termVar[_|_]»","verifiedBy":[]},{"category":"computationalOperation","hasSorry":false,"instanceArgTypes":[],"instanceDisposition":null,"instanceLawfulClass":null,"instanceOf":null,"isPrivate":false,"name":"ProbabilityTheory.condVar","verifiedBy":[{"bridgingDirection":null,"kind":"mathematicalProperty","name":"ProbabilityTheory.condVar_const"},{"bridgingDirection":null,"kind":"mathematicalProperty","name":"ProbabilityTheory.condVar_smul"},{"bridgingDirection":null,"kind":"mathematicalProperty","name":"ProbabilityTheory.integrable_condVar"},{"bridgingDirection":null,"kind":"mathematicalProperty","name":"ProbabilityTheory.integral_condVar_add_variance_condExp"},{"bridgingDirection":null,"kind":"mathematicalProperty","name":"ProbabilityTheory.condVar_of_stronglyMeasurable"},{"bridgingDirection":null,"kind":"mathematicalProperty","name":"ProbabilityTheory.condVar_zero"},{"bridgingDirection":null,"kind":"mathematicalProperty","name":"ProbabilityTheory.condVar_of_not_le"},{"bridgingDirection":null,"kind":"mathematicalProperty","name":"ProbabilityTheory.condVar_ae_le_condExp_sq"},{"bridgingDirection":null,"kind":"mathematicalProperty","name":"ProbabilityTheory.condVar_of_ae_eq_zero_or_one"},{"bridgingDirection":null,"kind":"mathematicalProperty","name":"ProbabilityTheory.condVar_bot'"},{"bridgingDirection":null,"kind":"mathematicalProperty","name":"ProbabilityTheory.condVar_of_sigmaFinite"},{"bridgingDirection":null,"kind":"mathematicalProperty","name":"ProbabilityTheory.setIntegral_condVar"},{"bridgingDirection":null,"kind":"mathematicalProperty","name":"ProbabilityTheory.condVar_neg"},{"bridgingDirection":null,"kind":"mathematicalProperty","name":"ProbabilityTheory.condVar_bot_ae_eq"},{"bridgingDirection":null,"kind":"mathematicalProperty","name":"ProbabilityTheory.condVar_of_aestronglyMeasurable"},{"bridgingDirection":null,"kind":"mathematicalProperty","name":"ProbabilityTheory.condVar_bot"},{"bridgingDirection":null,"kind":"mathematicalProperty","name":"ProbabilityTheory.condVar_of_not_sigmaFinite"},{"bridgingDirection":null,"kind":"mathematicalProperty","name":"ProbabilityTheory.condVar_of_not_integrable"},{"bridgingDirection":null,"kind":"mathematicalProperty","name":"ProbabilityTheory.condVar_ae_eq_condExp_sq_sub_sq_condExp"},{"bridgingDirection":null,"kind":"mathematicalProperty","name":"ProbabilityTheory.stronglyMeasurable_condVar"},{"bridgingDirection":null,"kind":"mathematicalProperty","name":"ProbabilityTheory.condVar_congr_ae"}]},{"category":"computationalOperation","hasSorry":false,"instanceArgTypes":[],"instanceDisposition":null,"instanceLawfulClass":null,"instanceOf":null,"isPrivate":false,"name":"ProbabilityTheory.«termVar[_;_|_]»","verifiedBy":[]}],"moduleName":"Mathlib.Probability.CondVar","theorems":[{"assumes":["MeasurableSpace","MeasurableSpace.instLE"],"axiomDeps":[],"bridgingDirection":null,"dependsOn":["eq_or_ne","ProbabilityTheory.condVar_zero","MeasureTheory.condExp_const","sub_self","zero_pow","Nat.instCharZero","Nat.instAtLeastTwoHAddOfNat","MeasureTheory.condExp_zero","MeasureTheory.condExp_of_not_integrable","MeasureTheory.integrable_const_iff_isFiniteMeasure","sub_zero","pow_ne_zero","isReduced_of_noZeroDivisors","NormMulClass.toNoZeroDivisors","NormedDivisionRing.toNormMulClass"],"hasSorry":false,"isPrivate":false,"kind":"mathematicalProperty","name":"ProbabilityTheory.condVar_const","proofDepTimeMs":10,"proves":["ProbabilityTheory.condVar","Pi.instZero","Real","Real.instZero"],"validates":[]},{"assumes":[],"axiomDeps":[],"bridgingDirection":null,"dependsOn":["MeasureTheory.Measure.instOuterMeasureClass","MeasureTheory.condExp_congr_ae","Real.instCompleteSpace","Filter.mp_mem","MeasureTheory.condExp_smul","Filter.univ_mem'","mul_pow"],"hasSorry":false,"isPrivate":false,"kind":"mathematicalProperty","name":"ProbabilityTheory.condVar_smul","proofDepTimeMs":5,"proves":["Filter.EventuallyEq","Real","MeasureTheory.ae","MeasureTheory.Measure","MeasureTheory.Measure.instFunLike","MeasureTheory.Measure.instOuterMeasureClass","ProbabilityTheory.condVar","Function.hasSMul","Real.instMul","Monoid.toPow","Real.instMonoid"],"validates":[]},{"assumes":[],"axiomDeps":[],"bridgingDirection":null,"dependsOn":["MeasureTheory.integrable_condExp","Real.instCompleteSpace"],"hasSorry":false,"isPrivate":false,"kind":"mathematicalProperty","name":"ProbabilityTheory.integrable_condVar","proofDepTimeMs":1,"proves":["MeasureTheory.Integrable","Real","UniformSpace.toTopologicalSpace","PseudoMetricSpace.toUniformSpace","Real.pseudoMetricSpace","SeminormedAddGroup.toContinuousENorm","SeminormedAddCommGroup.toSeminormedAddGroup","NonUnitalSeminormedRing.toSeminormedAddCommGroup","NonUnitalSeminormedCommRing.toNonUnitalSeminormedRing","SeminormedCommRing.toNonUnitalSeminormedCommRing","NormedCommRing.toSeminormedCommRing","Real.normedCommRing","ProbabilityTheory.condVar"],"validates":[]},{"assumes":["MeasurableSpace","MeasurableSpace.instLE","MeasureTheory.MemLp","Real","ContinuousENorm.toENorm","UniformSpace.toTopologicalSpace","PseudoMetricSpace.toUniformSpace","SeminormedAddGroup.toPseudoMetricSpace","SeminormedAddCommGroup.toSeminormedAddGroup","NonUnitalSeminormedRing.toSeminormedAddCommGroup","NonUnitalSeminormedCommRing.toNonUnitalSeminormedRing","SeminormedCommRing.toNonUnitalSeminormedCommRing","NormedCommRing.toSeminormedCommRing","Real.normedCommRing","SeminormedAddGroup.toContinuousENorm","Real.pseudoMetricSpace","ENNReal","instOfNatAtLeastTwo","AddMonoidWithOne.toNatCast","AddCommMonoidWithOne.toAddMonoidWithOne","ENNReal.instAddCommMonoidWithOne","Nat.instAtLeastTwoHAddOfNat"],"axiomDeps":[],"bridgingDirection":null,"dependsOn":["Nat.instAtLeastTwoHAddOfNat","MeasureTheory.integral_congr_ae","ProbabilityTheory.condVar_ae_eq_condExp_sq_sub_sq_condExp","MeasureTheory.IsZeroOrProbabilityMeasure.toIsFiniteMeasure","MeasureTheory.instIsZeroOrProbabilityMeasureOfIsProbabilityMeasure","ProbabilityTheory.variance_eq_sub","MeasureTheory.MemLp.condExp","Real.instCompleteSpace","MeasureTheory.integral_sub'","MeasureTheory.integrable_condExp","MeasureTheory.MemLp.integrable_sq","MeasureTheory.integral_condExp","MeasureTheory.IsFiniteMeasure.toSigmaFinite","MeasureTheory.isFiniteMeasure_trim","Mathlib.Tactic.Ring.of_eq","Mathlib.Tactic.Ring.Common.add_congr","Mathlib.Tactic.Ring.Common.sub_congr","Mathlib.Tactic.Ring.Common.atom_pf","Mathlib.Tactic.Ring.Common.sub_pf","Mathlib.Tactic.Ring.Common.neg_add","Mathlib.Tactic.Ring.Common.neg_mul","Mathlib.Meta.NormNum.IsInt.to_raw_eq","Mathlib.Meta.NormNum.isInt_neg","Mathlib.Meta.NormNum.IsNat.to_isInt","Mathlib.Meta.NormNum.IsNat.of_raw","Mathlib.Tactic.Ring.Common.neg_zero","Mathlib.Tactic.Ring.Common.add_pf_add_lt","Mathlib.Tactic.Ring.Common.add_pf_zero_add","Mathlib.Tactic.Ring.Common.pow_congr","Mathlib.Tactic.Ring.cast_pos","Mathlib.Meta.NormNum.isNat_ofNat","Mathlib.Tactic.Ring.Common.pow_add","Mathlib.Tactic.Ring.Common.single_pow","Mathlib.Tactic.Ring.Common.mul_pow_mul","Mathlib.Meta.NormNum.IsNat.to_raw_eq","Mathlib.Meta.NormNum.isNat_mul","Mathlib.Tactic.Ring.Common.one_pow","Mathlib.Tactic.Ring.Common.mul_pf_left","Mathlib.Tactic.Ring.Common.pow_zero","Mathlib.Tactic.Ring.Common.add_mul","Mathlib.Tactic.Ring.Common.mul_add","Mathlib.Tactic.Ring.Common.mul_zero","Mathlib.Tactic.Ring.Common.add_pf_add_zero","Mathlib.Tactic.Ring.Common.zero_mul","Mathlib.Tactic.Ring.Common.add_pf_add_overlap_zero","Mathlib.Tactic.Ring.Common.add_overlap_pf_zero","Mathlib.Meta.NormNum.IsInt.to_isNat","Mathlib.Meta.NormNum.isInt_add","Mathlib.Meta.NormNum.IsInt.of_raw"],"hasSorry":false,"isPrivate":false,"kind":"mathematicalProperty","name":"ProbabilityTheory.integral_condVar_add_variance_condExp","proofDepTimeMs":23,"proves":["Real","Real.instAdd","MeasureTheory.integral","Real.normedAddCommGroup","InnerProductSpace.toNormedSpace","Real.instRCLike","NormedAddCommGroup.toSeminormedAddCommGroup","RCLike.toInnerProductSpaceReal","ProbabilityTheory.condVar","ProbabilityTheory.variance","MeasureTheory.condExp"],"validates":[]},{"assumes":["MeasurableSpace","MeasurableSpace.instLE","MeasureTheory.StronglyMeasurable","Real","UniformSpace.toTopologicalSpace","PseudoMetricSpace.toUniformSpace","Real.pseudoMetricSpace","MeasureTheory.Integrable","SeminormedAddGroup.toContinuousENorm","SeminormedAddCommGroup.toSeminormedAddGroup","NonUnitalSeminormedRing.toSeminormedAddCommGroup","NonUnitalSeminormedCommRing.toNonUnitalSeminormedRing","SeminormedCommRing.toNonUnitalSeminormedCommRing","NormedCommRing.toSeminormedCommRing","Real.normedCommRing","Monoid.toPow","Pi.monoid","Real.instMonoid","Pi.instSub","Real.instSub","MeasureTheory.condExp","Real.normedAddCommGroup","InnerProductSpace.toNormedSpace","Real.instRCLike","NormedAddCommGroup.toSeminormedAddCommGroup","RCLike.toInnerProductSpaceReal"],"axiomDeps":[],"bridgingDirection":null,"dependsOn":["MeasureTheory.condExp_of_stronglyMeasurable","MeasureTheory.StronglyMeasurable.pow","IsTopologicalSemiring.toContinuousMul","IsTopologicalRing.toIsTopologicalSemiring","instIsTopologicalRingReal","MeasureTheory.StronglyMeasurable.sub","IsTopologicalAddGroup.to_continuousSub","instIsTopologicalAddGroupReal","MeasureTheory.stronglyMeasurable_condExp"],"hasSorry":false,"isPrivate":false,"kind":"mathematicalProperty","name":"ProbabilityTheory.condVar_of_stronglyMeasurable","proofDepTimeMs":4,"proves":["ProbabilityTheory.condVar","Real","Monoid.toPow","Real.instMonoid","Real.instSub","MeasureTheory.condExp","Real.normedAddCommGroup","InnerProductSpace.toNormedSpace","Real.instRCLike","NormedAddCommGroup.toSeminormedAddCommGroup","RCLike.toInnerProductSpaceReal"],"validates":[]},{"assumes":[],"axiomDeps":[],"bridgingDirection":null,"dependsOn":["MeasureTheory.condExp_zero","sub_self","zero_pow","Nat.instCharZero","Nat.instAtLeastTwoHAddOfNat"],"hasSorry":false,"isPrivate":false,"kind":"mathematicalProperty","name":"ProbabilityTheory.condVar_zero","proofDepTimeMs":5,"proves":["ProbabilityTheory.condVar","Pi.instZero","Real","Real.instZero"],"validates":[]},{"assumes":["MeasurableSpace","MeasurableSpace.instLE"],"axiomDeps":[],"bridgingDirection":null,"dependsOn":["MeasureTheory.condExp_of_not_le"],"hasSorry":false,"isPrivate":false,"kind":"mathematicalProperty","name":"ProbabilityTheory.condVar_of_not_le","proofDepTimeMs":0,"proves":["ProbabilityTheory.condVar","Pi.instZero","Real","Real.instZero"],"validates":[]},{"assumes":["MeasurableSpace","MeasurableSpace.instLE","MeasureTheory.MemLp","Real","ContinuousENorm.toENorm","UniformSpace.toTopologicalSpace","PseudoMetricSpace.toUniformSpace","SeminormedAddGroup.toPseudoMetricSpace","SeminormedAddCommGroup.toSeminormedAddGroup","NonUnitalSeminormedRing.toSeminormedAddCommGroup","NonUnitalSeminormedCommRing.toNonUnitalSeminormedRing","SeminormedCommRing.toNonUnitalSeminormedCommRing","NormedCommRing.toSeminormedCommRing","Real.normedCommRing","SeminormedAddGroup.toContinuousENorm","Real.pseudoMetricSpace","ENNReal","instOfNatAtLeastTwo","AddMonoidWithOne.toNatCast","AddCommMonoidWithOne.toAddMonoidWithOne","ENNReal.instAddCommMonoidWithOne","Nat.instAtLeastTwoHAddOfNat"],"axiomDeps":[],"bridgingDirection":null,"dependsOn":["Nat.instAtLeastTwoHAddOfNat","Filter.mp_mem","MeasureTheory.Measure.instOuterMeasureClass","ProbabilityTheory.condVar_ae_eq_condExp_sq_sub_sq_condExp","Filter.univ_mem'","le_of_not_gt","Mathlib.Tactic.Linarith.lt_irrefl","Mathlib.Tactic.Ring.of_eq","Mathlib.Tactic.Ring.Common.add_congr","Mathlib.Tactic.Ring.Common.sub_congr","Mathlib.Tactic.Ring.cast_zero","Mathlib.Meta.NormNum.isNat_ofNat","Nat.cast_zero","Mathlib.Tactic.Ring.Common.pow_congr","Mathlib.Tactic.Ring.Common.atom_pf","Mathlib.Tactic.Ring.cast_pos","Mathlib.Tactic.Ring.Common.pow_add","Mathlib.Tactic.Ring.Common.single_pow","Mathlib.Tactic.Ring.Common.mul_pow_mul","Mathlib.Meta.NormNum.IsNat.to_raw_eq","Mathlib.Meta.NormNum.isNat_mul","Mathlib.Meta.NormNum.IsNat.of_raw","Mathlib.Tactic.Ring.Common.one_pow","Mathlib.Tactic.Ring.Common.mul_pf_left","Mathlib.Tactic.Ring.Common.pow_zero","Mathlib.Tactic.Ring.Common.add_mul","Mathlib.Tactic.Ring.Common.mul_add","Mathlib.Tactic.Ring.Common.mul_zero","Mathlib.Tactic.Ring.Common.add_pf_add_zero","Mathlib.Tactic.Ring.Common.zero_mul","Mathlib.Tactic.Ring.Common.sub_pf","Mathlib.Tactic.Ring.Common.neg_add","Mathlib.Tactic.Ring.Common.neg_mul","Mathlib.Meta.NormNum.IsInt.to_raw_eq","Mathlib.Meta.NormNum.isInt_neg","Mathlib.Meta.NormNum.IsNat.to_isInt","Mathlib.Tactic.Ring.Common.neg_zero","Mathlib.Tactic.Ring.Common.add_pf_zero_add","Mathlib.Tactic.Ring.Common.add_pf_add_gt","Mathlib.Meta.NormNum.IsInt.to_isNat","Mathlib.Meta.NormNum.IsInt.of_raw","Mathlib.Tactic.Ring.Common.add_pf_add_lt","Mathlib.Tactic.Ring.Common.add_pf_add_overlap_zero","Mathlib.Tactic.Ring.Common.add_overlap_pf_zero","Mathlib.Meta.NormNum.isInt_add","Mathlib.Tactic.Linarith.add_lt_of_le_of_neg","Real.instIsStrictOrderedRing","Mathlib.Tactic.Linarith.le_of_le_of_eq","Mathlib.Tactic.Linarith.sub_nonpos_of_le","Real.instIsOrderedRing","sq_nonneg","AddGroup.existsAddOfLE","IsOrderedRing.toPosMulMono","IsOrderedAddMonoid.toAddLeftMono","Real.instIsOrderedAddMonoid","sub_eq_zero_of_eq","Mathlib.Tactic.Linarith.sub_neg_of_lt"],"hasSorry":false,"isPrivate":false,"kind":"mathematicalProperty","name":"ProbabilityTheory.condVar_ae_le_condExp_sq","proofDepTimeMs":27,"proves":["Filter.EventuallyLE","Real","Real.instLE","MeasureTheory.ae","MeasureTheory.Measure","MeasureTheory.Measure.instFunLike","MeasureTheory.Measure.instOuterMeasureClass","ProbabilityTheory.condVar","MeasureTheory.condExp","Real.normedAddCommGroup","InnerProductSpace.toNormedSpace","Real.instRCLike","NormedAddCommGroup.toSeminormedAddCommGroup","RCLike.toInnerProductSpaceReal","Monoid.toPow","Pi.monoid","Real.instMonoid"],"validates":[]},{"assumes":[],"axiomDeps":[],"bridgingDirection":null,"dependsOn":["MeasureTheory.condExp_bot'","Real.instCompleteSpace","IsScalarTower.right","MeasureTheory.integral_smul_measure","ENNReal.toReal_inv"],"hasSorry":false,"isPrivate":false,"kind":"mathematicalProperty","name":"ProbabilityTheory.condVar_bot'","proofDepTimeMs":5,"proves":["ProbabilityTheory.condVar","Bot.bot","MeasurableSpace","OrderBot.toBot","Preorder.toLE","PartialOrder.toPreorder","SemilatticeSup.toPartialOrder","Lattice.toSemilatticeSup","CompleteLattice.toLattice","MeasurableSpace.instCompleteLattice","BoundedOrder.toOrderBot","CompleteLattice.toBoundedOrder","MeasureTheory.average","Real","Real.normedAddCommGroup","InnerProductSpace.toNormedSpace","Real.instRCLike","NormedAddCommGroup.toSeminormedAddCommGroup","RCLike.toInnerProductSpaceReal","Monoid.toPow","Real.instMonoid","Real.instSub"],"validates":[]},{"assumes":["MeasurableSpace","MeasurableSpace.instLE"],"axiomDeps":[],"bridgingDirection":null,"dependsOn":["MeasureTheory.condExp_of_sigmaFinite"],"hasSorry":false,"isPrivate":false,"kind":"mathematicalProperty","name":"ProbabilityTheory.condVar_of_sigmaFinite","proofDepTimeMs":1,"proves":["ProbabilityTheory.condVar","MeasureTheory.Integrable","Real","UniformSpace.toTopologicalSpace","PseudoMetricSpace.toUniformSpace","Real.pseudoMetricSpace","SeminormedAddGroup.toContinuousENorm","SeminormedAddCommGroup.toSeminormedAddGroup","NonUnitalSeminormedRing.toSeminormedAddCommGroup","NonUnitalSeminormedCommRing.toNonUnitalSeminormedRing","SeminormedCommRing.toNonUnitalSeminormedCommRing","NormedCommRing.toSeminormedCommRing","Real.normedCommRing","Monoid.toPow","Real.instMonoid","Real.instSub","MeasureTheory.condExp","Real.normedAddCommGroup","InnerProductSpace.toNormedSpace","Real.instRCLike","NormedAddCommGroup.toSeminormedAddCommGroup","RCLike.toInnerProductSpaceReal","MeasureTheory.StronglyMeasurable","SeminormedAddCommGroup.toPseudoMetricSpace","MeasureTheory.AEEqFun.cast","MeasureTheory.AEEqFun","AddSubgroup","MeasureTheory.AEEqFun.instAddGroup","AddCommGroup.toAddGroup","NormedAddCommGroup.toAddCommGroup","SetLike.instMembership","AddSubgroup.instSetLike","MeasureTheory.Lp","ENNReal","ENNReal.instOne","MeasureTheory.condExpL1","MeasureTheory.aestronglyMeasurable_condExpL1","Pi.instZero","Real.instZero"],"validates":[]},{"assumes":["MeasurableSpace","MeasurableSpace.instLE","MeasureTheory.Integrable","Real","UniformSpace.toTopologicalSpace","PseudoMetricSpace.toUniformSpace","Real.pseudoMetricSpace","SeminormedAddGroup.toContinuousENorm","SeminormedAddCommGroup.toSeminormedAddGroup","NonUnitalSeminormedRing.toSeminormedAddCommGroup","NonUnitalSeminormedCommRing.toNonUnitalSeminormedRing","SeminormedCommRing.toNonUnitalSeminormedCommRing","NormedCommRing.toSeminormedCommRing","Real.normedCommRing","Monoid.toPow","Pi.monoid","Real.instMonoid","Pi.instSub","Real.instSub","MeasureTheory.condExp","Real.normedAddCommGroup","InnerProductSpace.toNormedSpace","Real.instRCLike","NormedAddCommGroup.toSeminormedAddCommGroup","RCLike.toInnerProductSpaceReal","MeasurableSet"],"axiomDeps":[],"bridgingDirection":null,"dependsOn":["MeasureTheory.setIntegral_condExp","Real.instCompleteSpace"],"hasSorry":false,"isPrivate":false,"kind":"mathematicalProperty","name":"ProbabilityTheory.setIntegral_condVar","proofDepTimeMs":1,"proves":["MeasureTheory.integral","Real","Real.normedAddCommGroup","InnerProductSpace.toNormedSpace","Real.instRCLike","NormedAddCommGroup.toSeminormedAddCommGroup","RCLike.toInnerProductSpaceReal","MeasureTheory.Measure.restrict","ProbabilityTheory.condVar","Monoid.toPow","Real.instMonoid","Real.instSub","MeasureTheory.condExp"],"validates":[]},{"assumes":[],"axiomDeps":[],"bridgingDirection":null,"dependsOn":["MeasureTheory.condExp_congr_ae","Real.instCompleteSpace","Filter.mp_mem","MeasureTheory.Measure.instOuterMeasureClass","MeasureTheory.condExp_neg","Filter.univ_mem'","sub_neg_eq_add","Mathlib.Tactic.Ring.of_eq","Mathlib.Tactic.Ring.Common.pow_congr","Mathlib.Tactic.Ring.Common.add_congr","Mathlib.Tactic.Ring.Common.neg_congr","Mathlib.Tactic.Ring.Common.atom_pf","Mathlib.Tactic.Ring.Common.neg_add","Mathlib.Tactic.Ring.Common.neg_mul","Mathlib.Meta.NormNum.IsInt.to_raw_eq","Mathlib.Meta.NormNum.isInt_neg","Mathlib.Meta.NormNum.IsNat.to_isInt","Mathlib.Meta.NormNum.IsNat.of_raw","Mathlib.Tactic.Ring.Common.neg_zero","Mathlib.Tactic.Ring.Common.add_pf_add_lt","Mathlib.Tactic.Ring.Common.add_pf_zero_add","Mathlib.Tactic.Ring.cast_pos","Mathlib.Meta.NormNum.isNat_ofNat","Mathlib.Tactic.Ring.Common.pow_add","Mathlib.Tactic.Ring.Common.pow_nat","Mathlib.Tactic.Ring.Common.coeff_one","Mathlib.Tactic.Ring.Common.pow_one_cast_of_isNat","Mathlib.Tactic.Ring.Common.pow_bit0","Mathlib.Tactic.Ring.Common.pow_one","Mathlib.Tactic.Ring.Common.add_mul","Mathlib.Tactic.Ring.Common.mul_add","Mathlib.Tactic.Ring.Common.mul_pp_pf_overlap","Mathlib.Meta.NormNum.IsNat.to_raw_eq","Mathlib.Meta.NormNum.isNat_add","Mathlib.Meta.NormNum.IsInt.to_isNat","Mathlib.Meta.NormNum.isInt_mul","Mathlib.Meta.NormNum.IsInt.of_raw","Mathlib.Tactic.Ring.Common.mul_pf_left","Mathlib.Tactic.Ring.Common.mul_pf_right","Mathlib.Tactic.Ring.Common.mul_zero","Mathlib.Tactic.Ring.Common.add_pf_add_zero","Mathlib.Tactic.Ring.Common.add_pf_add_gt","Mathlib.Meta.NormNum.isNat_mul","Mathlib.Tactic.Ring.Common.zero_mul","Mathlib.Tactic.Ring.Common.add_pf_add_overlap","Mathlib.Tactic.Ring.Common.add_overlap_pf","Mathlib.Meta.NormNum.isInt_add","Mathlib.Tactic.Ring.Common.pow_zero","Mathlib.Tactic.Ring.Common.sub_congr","Mathlib.Tactic.Ring.Common.sub_pf"],"hasSorry":false,"isPrivate":false,"kind":"mathematicalProperty","name":"ProbabilityTheory.condVar_neg","proofDepTimeMs":23,"proves":["Filter.EventuallyEq","Real","MeasureTheory.ae","MeasureTheory.Measure","MeasureTheory.Measure.instFunLike","MeasureTheory.Measure.instOuterMeasureClass","ProbabilityTheory.condVar","Pi.instNeg","Real.instNeg"],"validates":[]},{"assumes":[],"axiomDeps":[],"bridgingDirection":null,"dependsOn":["MeasureTheory.Measure.instOuterMeasureClass","eq_zero_or_neZero","MeasureTheory.ae_zero","Filter.eventually_bot","Filter.Eventually.of_forall","ProbabilityTheory.condVar_bot'"],"hasSorry":false,"isPrivate":false,"kind":"mathematicalProperty","name":"ProbabilityTheory.condVar_bot_ae_eq","proofDepTimeMs":4,"proves":["Filter.EventuallyEq","Real","MeasureTheory.ae","MeasureTheory.Measure","MeasureTheory.Measure.instFunLike","MeasureTheory.Measure.instOuterMeasureClass","ProbabilityTheory.condVar","Bot.bot","MeasurableSpace","OrderBot.toBot","Preorder.toLE","PartialOrder.toPreorder","SemilatticeSup.toPartialOrder","Lattice.toSemilatticeSup","CompleteLattice.toLattice","MeasurableSpace.instCompleteLattice","BoundedOrder.toOrderBot","CompleteLattice.toBoundedOrder","MeasureTheory.average","Real.normedAddCommGroup","InnerProductSpace.toNormedSpace","Real.instRCLike","NormedAddCommGroup.toSeminormedAddCommGroup","RCLike.toInnerProductSpaceReal","Monoid.toPow","Real.instMonoid","Real.instSub"],"validates":[]},{"assumes":["MeasurableSpace","MeasurableSpace.instLE","MeasureTheory.AEStronglyMeasurable","Real","UniformSpace.toTopologicalSpace","PseudoMetricSpace.toUniformSpace","Real.pseudoMetricSpace","MeasureTheory.Integrable","SeminormedAddGroup.toContinuousENorm","SeminormedAddCommGroup.toSeminormedAddGroup","NonUnitalSeminormedRing.toSeminormedAddCommGroup","NonUnitalSeminormedCommRing.toNonUnitalSeminormedRing","SeminormedCommRing.toNonUnitalSeminormedCommRing","NormedCommRing.toSeminormedCommRing","Real.normedCommRing","Monoid.toPow","Pi.monoid","Real.instMonoid","Pi.instSub","Real.instSub","MeasureTheory.condExp","Real.normedAddCommGroup","InnerProductSpace.toNormedSpace","Real.instRCLike","NormedAddCommGroup.toSeminormedAddCommGroup","RCLike.toInnerProductSpaceReal"],"axiomDeps":[],"bridgingDirection":null,"dependsOn":["MeasureTheory.condExp_of_aestronglyMeasurable'","Real.instCompleteSpace","Continuous.comp_aestronglyMeasurable","continuous_pow","IsTopologicalSemiring.toContinuousMul","IsTopologicalRing.toIsTopologicalSemiring","instIsTopologicalRingReal","MeasureTheory.AEStronglyMeasurable.sub","instIsTopologicalAddGroupReal","MeasureTheory.StronglyMeasurable.aestronglyMeasurable","MeasureTheory.stronglyMeasurable_condExp"],"hasSorry":false,"isPrivate":false,"kind":"mathematicalProperty","name":"ProbabilityTheory.condVar_of_aestronglyMeasurable","proofDepTimeMs":5,"proves":["Filter.EventuallyEq","Real","MeasureTheory.ae","MeasureTheory.Measure","MeasureTheory.Measure.instFunLike","MeasureTheory.Measure.instOuterMeasureClass","ProbabilityTheory.condVar","Monoid.toPow","Pi.monoid","Real.instMonoid","Pi.instSub","Real.instSub","MeasureTheory.condExp","Real.normedAddCommGroup","InnerProductSpace.toNormedSpace","Real.instRCLike","NormedAddCommGroup.toSeminormedAddCommGroup","RCLike.toInnerProductSpaceReal"],"validates":[]},{"assumes":["AEMeasurable","Real","Real.measurableSpace"],"axiomDeps":[],"bridgingDirection":null,"dependsOn":["ProbabilityTheory.condVar_bot'","MeasureTheory.IsProbabilityMeasure.neZero","MeasureTheory.average_eq_integral","ProbabilityTheory.variance_eq_integral"],"hasSorry":false,"isPrivate":false,"kind":"mathematicalProperty","name":"ProbabilityTheory.condVar_bot","proofDepTimeMs":5,"proves":["ProbabilityTheory.condVar","Bot.bot","MeasurableSpace","OrderBot.toBot","Preorder.toLE","PartialOrder.toPreorder","SemilatticeSup.toPartialOrder","Lattice.toSemilatticeSup","CompleteLattice.toLattice","MeasurableSpace.instCompleteLattice","BoundedOrder.toOrderBot","CompleteLattice.toBoundedOrder","ProbabilityTheory.variance"],"validates":[]},{"assumes":["MeasurableSpace","MeasurableSpace.instLE","MeasureTheory.SigmaFinite","MeasureTheory.Measure.trim"],"axiomDeps":[],"bridgingDirection":null,"dependsOn":["MeasureTheory.condExp_of_not_sigmaFinite"],"hasSorry":false,"isPrivate":false,"kind":"mathematicalProperty","name":"ProbabilityTheory.condVar_of_not_sigmaFinite","proofDepTimeMs":0,"proves":["ProbabilityTheory.condVar","Pi.instZero","Real","Real.instZero"],"validates":[]},{"assumes":["MeasureTheory.Integrable","Real","UniformSpace.toTopologicalSpace","PseudoMetricSpace.toUniformSpace","Real.pseudoMetricSpace","SeminormedAddGroup.toContinuousENorm","SeminormedAddCommGroup.toSeminormedAddGroup","NonUnitalSeminormedRing.toSeminormedAddCommGroup","NonUnitalSeminormedCommRing.toNonUnitalSeminormedRing","SeminormedCommRing.toNonUnitalSeminormedCommRing","NormedCommRing.toSeminormedCommRing","Real.normedCommRing","Monoid.toPow","Real.instMonoid","Real.instSub","MeasureTheory.condExp","Real.normedAddCommGroup","InnerProductSpace.toNormedSpace","Real.instRCLike","NormedAddCommGroup.toSeminormedAddCommGroup","RCLike.toInnerProductSpaceReal"],"axiomDeps":[],"bridgingDirection":null,"dependsOn":["MeasureTheory.condExp_of_not_integrable"],"hasSorry":false,"isPrivate":false,"kind":"mathematicalProperty","name":"ProbabilityTheory.condVar_of_not_integrable","proofDepTimeMs":1,"proves":["ProbabilityTheory.condVar","Pi.instZero","Real","Real.instZero"],"validates":[]},{"assumes":["MeasurableSpace","MeasurableSpace.instLE","MeasureTheory.MemLp","Real","ContinuousENorm.toENorm","UniformSpace.toTopologicalSpace","PseudoMetricSpace.toUniformSpace","SeminormedAddGroup.toPseudoMetricSpace","SeminormedAddCommGroup.toSeminormedAddGroup","NonUnitalSeminormedRing.toSeminormedAddCommGroup","NonUnitalSeminormedCommRing.toNonUnitalSeminormedRing","SeminormedCommRing.toNonUnitalSeminormedCommRing","NormedCommRing.toSeminormedCommRing","Real.normedCommRing","SeminormedAddGroup.toContinuousENorm","Real.pseudoMetricSpace","ENNReal","instOfNatAtLeastTwo","AddMonoidWithOne.toNatCast","AddCommMonoidWithOne.toAddMonoidWithOne","ENNReal.instAddCommMonoidWithOne","Nat.instAtLeastTwoHAddOfNat"],"axiomDeps":[],"bridgingDirection":null,"dependsOn":["Nat.instAtLeastTwoHAddOfNat","MeasureTheory.Measure.instOuterMeasureClass","sub_sq","MeasureTheory.MemLp.integrable_sq","mul_assoc","MeasureTheory.Integrable.const_mul","MeasureTheory.memLp_one_iff_integrable","MeasureTheory.MemLp.mul","MeasureTheory.MemLp.condExp","Real.instCompleteSpace","ENNReal.HolderConjugate.instTwoTwo","Rat.instIsStrictOrderedRing","Filter.mp_mem","MeasureTheory.condExp_ofNat","MeasureTheory.condExp_mul_of_stronglyMeasurable_right","MeasureTheory.stronglyMeasurable_condExp","MeasureTheory.MemLp.integrable","one_le_two","IsOrderedRing.toZeroLEOneClass","ENNReal.instIsOrderedRing","IsOrderedAddMonoid.toAddLeftMono","ENNReal.instIsOrderedAddMonoid","MeasureTheory.condExp_sub","MeasureTheory.condExp_add","MeasureTheory.Integrable.sub","Filter.univ_mem'","MeasureTheory.condExp_of_stronglyMeasurable","MeasureTheory.IsFiniteMeasure.toSigmaFinite","MeasureTheory.isFiniteMeasure_trim","MeasureTheory.StronglyMeasurable.pow","IsTopologicalSemiring.toContinuousMul","IsTopologicalRing.toIsTopologicalSemiring","instIsTopologicalRingReal","instIsRightCancelAddOfAddRightReflectLE","addRightReflectLE_of_addLeftReflectLE","IsLeftCancelAdd.addLeftReflectLE_of_addLeftReflectLT","AddLeftCancelSemigroup.toIsLeftCancelAdd","contravariant_lt_of_covariant_le","Real.instIsOrderedAddMonoid","sq","Mathlib.Tactic.Ring.of_eq","Mathlib.Tactic.Ring.Common.add_congr","Mathlib.Tactic.Ring.Common.sub_congr","Mathlib.Tactic.Ring.Common.atom_pf","Mathlib.Tactic.Ring.Common.mul_congr","Mathlib.Tactic.Ring.cast_pos","Mathlib.Meta.NormNum.isNat_ofNat","Mathlib.Meta.NormNum.instAtLeastTwo","Mathlib.Tactic.Ring.Common.pow_congr","Mathlib.Tactic.Ring.Common.pow_add","Mathlib.Tactic.Ring.Common.single_pow","Mathlib.Tactic.Ring.Common.mul_pow_mul","Mathlib.Meta.NormNum.IsNat.to_raw_eq","Mathlib.Meta.NormNum.isNat_mul","Mathlib.Meta.NormNum.IsNat.of_raw","Mathlib.Tactic.Ring.Common.one_pow","Mathlib.Tactic.Ring.Common.mul_pf_left","Mathlib.Tactic.Ring.Common.pow_zero","Mathlib.Tactic.Ring.Common.add_mul","Mathlib.Tactic.Ring.Common.mul_add","Mathlib.Tactic.Ring.Common.mul_zero","Mathlib.Tactic.Ring.Common.add_pf_add_zero","Mathlib.Tactic.Ring.Common.zero_mul","Mathlib.Tactic.Ring.Common.mul_pf_right","Mathlib.Tactic.Ring.Common.sub_pf","Mathlib.Tactic.Ring.Common.neg_add","Mathlib.Tactic.Ring.Common.neg_mul","Mathlib.Meta.NormNum.IsInt.to_raw_eq","Mathlib.Meta.NormNum.isInt_neg","Mathlib.Meta.NormNum.IsNat.to_isInt","Mathlib.Tactic.Ring.Common.neg_zero","Mathlib.Tactic.Ring.Common.add_pf_add_lt","Mathlib.Tactic.Ring.Common.add_pf_zero_add","Mathlib.Tactic.Ring.Common.add_pf_add_overlap","Mathlib.Tactic.Ring.Common.add_overlap_pf","Mathlib.Meta.NormNum.isInt_add","Mathlib.Meta.NormNum.IsInt.of_raw"],"hasSorry":false,"isPrivate":false,"kind":"mathematicalProperty","name":"ProbabilityTheory.condVar_ae_eq_condExp_sq_sub_sq_condExp","proofDepTimeMs":38,"proves":["Filter.EventuallyEq","Real","MeasureTheory.ae","MeasureTheory.Measure","MeasureTheory.Measure.instFunLike","MeasureTheory.Measure.instOuterMeasureClass","ProbabilityTheory.condVar","Pi.instSub","Real.instSub","MeasureTheory.condExp","Real.normedAddCommGroup","InnerProductSpace.toNormedSpace","Real.instRCLike","NormedAddCommGroup.toSeminormedAddCommGroup","RCLike.toInnerProductSpaceReal","Monoid.toPow","Pi.monoid","Real.instMonoid"],"validates":[]},{"assumes":[],"axiomDeps":[],"bridgingDirection":null,"dependsOn":["MeasureTheory.stronglyMeasurable_condExp"],"hasSorry":false,"isPrivate":false,"kind":"mathematicalProperty","name":"ProbabilityTheory.stronglyMeasurable_condVar","proofDepTimeMs":1,"proves":["MeasureTheory.StronglyMeasurable","Real","UniformSpace.toTopologicalSpace","PseudoMetricSpace.toUniformSpace","Real.pseudoMetricSpace","ProbabilityTheory.condVar"],"validates":[]},{"assumes":["Filter.EventuallyEq","Real","MeasureTheory.ae","MeasureTheory.Measure","MeasureTheory.Measure.instFunLike","MeasureTheory.Measure.instOuterMeasureClass"],"axiomDeps":[],"bridgingDirection":null,"dependsOn":["MeasureTheory.Measure.instOuterMeasureClass","MeasureTheory.condExp_congr_ae","Real.instCompleteSpace","Filter.mp_mem","Filter.univ_mem'"],"hasSorry":false,"isPrivate":false,"kind":"mathematicalProperty","name":"ProbabilityTheory.condVar_congr_ae","proofDepTimeMs":3,"proves":["Filter.EventuallyEq","Real","MeasureTheory.ae","MeasureTheory.Measure","MeasureTheory.Measure.instFunLike","MeasureTheory.Measure.instOuterMeasureClass","ProbabilityTheory.condVar"],"validates":[]}]}