{"definitions":[{"category":"computationalOperation","hasSorry":false,"instanceArgTypes":[],"instanceDisposition":null,"instanceLawfulClass":null,"instanceOf":null,"isPrivate":false,"name":"Cslib.LTS.commandCreate_lts__","verifiedBy":[]},{"category":"computationalOperation","hasSorry":false,"instanceArgTypes":[],"instanceDisposition":null,"instanceLawfulClass":null,"instanceOf":null,"isPrivate":false,"name":"Cslib.LTS.command_Lts_transition_notation__","verifiedBy":[]},{"category":"computationalOperation","hasSorry":false,"instanceArgTypes":[],"instanceDisposition":null,"instanceLawfulClass":null,"instanceOf":null,"isPrivate":false,"name":"Cslib.LTS.ltsAttr","verifiedBy":[]}],"moduleName":"Cslib.Foundations.Semantics.LTS.Notation","theorems":[]}